terminalUno/__init__.py
terminalUno/__main__.py
terminalUno/uno.py
terminaluno-1.0.1.dist-info/METADATA
terminaluno-1.0.1.dist-info/WHEEL
terminaluno-1.0.1.dist-info/entry_points.txt
terminaluno-1.0.1.dist-info/top_level.txt
terminaluno-1.0.1.dist-info/RECORD
