Metadata-Version: 2.4
Name: terminalUno
Version: 1.0.1
Summary: A python package
Author-email: Jiaxi Zhang <jz5751@nyu.edu>
License:                     GNU GENERAL PUBLIC LICENSE
Project-URL: Homepage, https://github.com/software-students-spring2025/3-python-package-se_project3
Project-URL: Repository, https://github.com/software-students-spring2025/3-python-package-se_project3.git
Project-URL: Bug Tracker, https://github.com/software-students-spring2025/3-python-package-se_project3/issues
Keywords: python,package,build,Uno,game
Classifier: Programming Language :: Python :: 3
Classifier: Intended Audience :: Education
Classifier: License :: OSI Approved :: GNU General Public License v3 (GPLv3)
Classifier: Operating System :: OS Independent
Requires-Python: >=3.7
Provides-Extra: dev
Requires-Dist: pytest; extra == "dev"
